kluck/__init__.py
kluck/classes/__init__.py
kluck/classes/kfalse.py
kluck/classes/ktrue.py
kluck/classes/maybe.py
kluck/functions/__init__.py
kluck/functions/conversions.py
kluck-0.0.2.dist-info/LICENSE
kluck-0.0.2.dist-info/METADATA
kluck-0.0.2.dist-info/WHEEL
kluck-0.0.2.dist-info/top_level.txt
kluck-0.0.2.dist-info/RECORD
