Metadata-Version: 2.1
Name: kluck
Version: 0.0.2
Summary: Awesome way to get lost in booleans with Kostya's Luck.
Author: Profitroll
License: GPLv3
Project-URL: Source, https://git.end-play.xyz/profitroll/kluck
Project-URL: Documentation, https://git.end-play.xyz/profitroll/kluck/wiki
Project-URL: Tracker, https://git.end-play.xyz/profitroll/kluck/issues
Classifier: Development Status :: 3 - Alpha
Classifier: Intended Audience :: Developers
Classifier: License :: OSI Approved :: GNU General Public License v3 (GPLv3)
Classifier: Operating System :: OS Independent
Classifier: Programming Language :: Python :: 3.0
Classifier: Programming Language :: Python :: 3.1
Classifier: Programming Language :: Python :: 3.2
Classifier: Programming Language :: Python :: 3.3
Classifier: Programming Language :: Python :: 3.4
Classifier: Programming Language :: Python :: 3.5
Classifier: Programming Language :: Python :: 3.6
Classifier: Programming Language :: Python :: 3.7
Classifier: Programming Language :: Python :: 3.8
Classifier: Programming Language :: Python :: 3.9
Classifier: Programming Language :: Python :: 3.10
Classifier: Programming Language :: Python :: 3.11
Classifier: Programming Language :: Python :: 3.12
Classifier: Programming Language :: Python :: 3.13
Classifier: Programming Language :: Python :: 3.14
Classifier: Topic :: Software Development :: Libraries :: Python Modules
Classifier: Topic :: Utilities
Requires-Python: >=3.0
License-File: LICENSE
Provides-Extra: dev
Requires-Dist: black==24.4.2; extra == "dev"
Requires-Dist: build==1.2.1; extra == "dev"
Requires-Dist: isort==5.13.2; extra == "dev"
Requires-Dist: mypy==1.10.1; extra == "dev"
Requires-Dist: pylint==3.2.5; extra == "dev"
Requires-Dist: pytest-cov==5.0.0; extra == "dev"
Requires-Dist: pytest==8.2.2; extra == "dev"
Requires-Dist: tox==4.16.0; extra == "dev"
